{"experiment_name": "nell_v1_ln_False_16_0.2_6_gru_lstm", "dataset": "nell_v1", "gpu": 7, "load_model": false, "train_file": "train", "valid_file": "valid", "num_epochs": 10, "early_stop": 50, "optimizer": "Adam", "lr": 0.0005, "l2": 0.0001, "using_jk": false, "loss": "bce", "margin": 10, "hop": 3, "un_hop": 1, "num_neg_samples_per_link": 1, "max_links": 1000000, "constrained_neg_prob": 0.0, "batch_size": 128, "num_workers": 8, "add_traspose_rels": true, "enclosing_sub_graph": false, "aug": false, "emb_dim": 16, "dropout": 0.2, "num_gcn_layers": 6, "message": "gru", "aggregate": "pna", "update": "lstm", "main_dir": "GNN", "exp_dir": "GNN/experiments/nell_v1_ln_False_16_0.2_6_gru_lstm"}